polygraphs/__init__.py
polygraphs/cli.py
polygraphs/graphs.py
polygraphs/hyperparameters.py
polygraphs/init.py
polygraphs/logger.py
polygraphs/logging.yaml
polygraphs/metadata.py
polygraphs/monitors.py
polygraphs/run.py
polygraphs/timer.py
polygraphs/visualisations.py
polygraphs/analysis/__init__.py
polygraphs/analysis/belief_processor.py
polygraphs/analysis/graph_converter.py
polygraphs/analysis/simulation_processor.py
polygraphs/datasets/__init__.py
polygraphs/datasets/dataset.py
polygraphs/datasets/francisbacon.py
polygraphs/datasets/ogb.py
polygraphs/datasets/snap.py
polygraphs/datasets/utils.py
polygraphs/ops/__init__.py
polygraphs/ops/common.py
polygraphs/ops/complex.py
polygraphs/ops/confessionals.py
polygraphs/ops/core.py
polygraphs/ops/math.py
polygraphs/ops/weightedops.py
polygraphs-0.0.23a0.dist-info/LICENSE
polygraphs-0.0.23a0.dist-info/METADATA
polygraphs-0.0.23a0.dist-info/WHEEL
polygraphs-0.0.23a0.dist-info/entry_points.txt
polygraphs-0.0.23a0.dist-info/top_level.txt
polygraphs-0.0.23a0.dist-info/RECORD
