Metadata-Version: 2.1
Name: polygraphs
Version: 0.0.23a0
Summary: Philosophical simulations on networks
Home-page: https://github.com/alexandroskoliousis/polygraphs
Author: Alexandros Koliousis
Author-email: Alexandros Koliousis <ak@akoliousis.com>, Amil Mohanan <amil@mohanan.net>
License: MIT License
Project-URL: Repository, https://github.com/alexandroskoliousis/polygraphs
Project-URL: Documentation, https://akoliousis.com/polygraphs/
Keywords: philosophy,epistemology,simulation
Requires-Python: >=3
License-File: LICENSE
Requires-Dist: PyYaml
Requires-Dist: pandas
Requires-Dist: numpy
Requires-Dist: h5py
Requires-Dist: matplotlib
Requires-Dist: networkx
Requires-Dist: six
Requires-Dist: torch
Requires-Dist: dgl
